fsm_assignment/problem3/vending_mealy.v
module vending_mealy(
    input  wire       clk,
    input  wire       rst,        // synchronous, active-high reset
    input  wire [1:0] coin,       // 01=5, 10=10, 00=idle
    output reg        dispense,   // 1-cycle pulse
    output reg        chg5,       // 1-cycle pulse when returning 5
    output reg [1:0]  state       // current FSM state
);

    // State encoding (total = 0,5,10,15)
    parameter S0  = 2'b00;
    parameter S5  = 2'b01;
    parameter S10 = 2'b10;
    parameter S15 = 2'b11;

    reg [1:0] current_state, next_state;

    // Sequential state update
    always @(posedge clk) begin
        if (rst)
            current_state <= S0;
        else
            current_state <= next_state;
    end

    // Combinational next state + outputs (Mealy)
    always @(*) begin
        // defaults
        next_state = current_state;
        dispense   = 0;
        chg5       = 0;
        state      = current_state;

        case (current_state)
            S0: begin
                if (coin == 2'b01)      next_state = S5;   // +5
                else if (coin == 2'b10) next_state = S10;  // +10
            end

            S5: begin
                if (coin == 2'b01)      next_state = S10;  // +5
                else if (coin == 2'b10) next_state = S15;  // +10
            end

            S10: begin
                if (coin == 2'b01)      next_state = S15;  // +5
                else if (coin == 2'b10) begin              // +10 = 20
                    dispense   = 1;
                    next_state = S0;
                end
            end

            S15: begin
                if (coin == 2'b01) begin                   // +5 = 20
                    dispense   = 1;
                    next_state = S0;
                end
                else if (coin == 2'b10) begin              // +10 = 25
                    dispense   = 1;
                    chg5       = 1;
                    next_state = S0;
                end
            end
        endcase
    end

endmodule

fsm_assignment/problem3/tb_vending_mealy.v
`timescale 1ns/1ns
`include "vending_mealy.v"

module tb_vending_mealy;

    reg clk, rst;
    reg [1:0] coin;
    wire [1:0] state;
    wire dispense, chg5;

    // DUT instantiation
    vending_mealy dut(
        .clk(clk),
        .rst(rst),
        .coin(coin),
        .state(state),
        .dispense(dispense),
        .chg5(chg5)
    );

    // Clock generation (10ns period)
    initial clk = 0;
    always #5 clk = ~clk;

    // Test sequence
    initial begin
        $dumpfile("vending_mealy.vcd");
        $dumpvars(0, tb_vending_mealy);

        $display("Time\t clk rst coin state dispense chg5");

        // Apply reset
        rst = 1; coin = 2'b00;
        #12; 
        rst = 0;

        // Insert 5 -> 10 -> 5 (total=20, dispense)
        coin = 2'b01; #10;  // +5
        coin = 2'b10; #10;  // +10
        coin = 2'b01; #10;  // +5 => dispense

        // Insert 10 -> 10 (total=20, dispense)
        coin = 2'b10; #10;
        coin = 2'b10; #10;

        // Insert 10 -> 10 -> 10 (total=30, should dispense + return 5)
        coin = 2'b10; #10;
        coin = 2'b10; #10;
        coin = 2'b10; #10;

        // Idle input
        coin = 2'b00; #20;

        $display("Simulation completed!");
        $finish;
    end

    // Monitor signals
    initial begin
        $monitor("%g\t %b   %b   %b    %b      %b        %b",
                 $time, clk, rst, coin, state, dispense, chg5);
    end

endmodule

fsm_assignment/problem3/waves/vending_mealy.vcd
$date
	Tue Aug 19 16:54:05 2025
$end
$version
	Icarus Verilog
$end
$timescale
	1ns
$end
$scope module tb_vending_mealy $end
$var wire 2 ! state [1:0] $end
$var wire 1 " dispense $end
$var wire 1 # chg5 $end
$var reg 1 $ clk $end
$var reg 2 % coin [1:0] $end
$var reg 1 & rst $end
$scope module dut $end
$var wire 1 $ clk $end
$var wire 2 ' coin [1:0] $end
$var wire 1 & rst $end
$var parameter 2 ( S0 $end
$var parameter 2 ) S10 $end
$var parameter 2 * S15 $end
$var parameter 2 + S5 $end
$var reg 1 # chg5 $end
$var reg 2 , current_state [1:0] $end
$var reg 1 " dispense $end
$var reg 2 - next_state [1:0] $end
$var reg 2 . state [1:0] $end
$upscope $end
$upscope $end
$enddefinitions $end
$comment Show the parameter values. $end
$dumpall
b1 +
b11 *
b10 )
b0 (
$end
#0
$dumpvars
bx .
bx -
bx ,
b0 '
1&
b0 %
0$
0#
0"
bx !
$end
#5
b0 !
b0 .
b0 -
b0 ,
1$
#10
0$
#12
b1 -
b1 %
b1 '
0&
#15
b10 -
b1 !
b1 .
b1 ,
1$
#20
0$
#22
b11 -
b10 %
b10 '
#25
b0 -
1#
1"
b11 !
b11 .
b11 ,
1$
#30
0$
#32
0#
1"
b0 -
b1 %
b1 '
#35
b1 -
b0 !
b0 .
0"
b0 ,
1$
#40
0$
#42
b10 -
b10 %
b10 '
#45
b0 -
1"
b10 !
b10 .
b10 ,
1$
#50
0$
#55
b10 -
b0 !
b0 .
0"
b0 ,
1$
#60
0$
#65
b0 -
1"
b10 !
b10 .
b10 ,
1$
#70
0$
#75
b10 -
b0 !
b0 .
0"
b0 ,
1$
#80
0$
#85
b0 -
1"
b10 !
b10 .
b10 ,
1$
#90
0$
#92
0"
b10 -
b0 %
b0 '
