Practice/Counter/counter.sv
`timescale 1ns/1ps


module counter #(
    parameter WIDTH=8
)(
    input logic clk,
    input logic rst_n,
    input logic en,
    input logic up,
    output logic [WIDTH-1:0] q
);

always_ff @(posedge clk or posedge rst_n) begin
    if(rst_n) q<='0;
    else if(en) q<= up ? (q+1'b1):(q-1'b1);
end

endmodule

Practice/Counter/tb_counter.sv
`timescale 1ns/1ps

module tb_counter;
 localparam WIDTH=4;
 logic clk=0,rst_n=0,en=0,up=1;
 logic [WIDTH-1:0] q;

 counter #(.WIDTH(WIDTH)) dut(.clk,.rst_n,.en,.up,.q);

 //100MHz-ish clk
 always #5 clk=~clk; //10ns clock preiod

 task step(input int n=1); repeat(n) @(posedge clk); endtask

 initial begin
    $dumpfile("counter.vcd"); $dumpvars(0,tb_counter);

    //release reset
    step(1);rst_n=1;step(1);rst_n=0;

    // count upto 3 steps
    en=1;up=1;step(3);
    assert(q==3) else $fatal(1,"count up failed,q=%0d",q);

    // count down to 2 steps
    up=0;step(2);
    assert(q==1) else $fatal(1,"down count failed,q=%0d",q);

    //hold
    en=0;step(3);
    assert(q==1) else $fatal(1,"hold failed");


    $display("Counter test finished");
    $finish;
 end
endmodule

Practice/Counter/counter.vcd
$date
	Fri Sep 26 06:11:44 2025
$end
$version
	Icarus Verilog
$end
$timescale
	1ps
$end
$scope module tb_counter $end
$var wire 4 ! q [3:0] $end
$var parameter 32 " WIDTH $end
$var reg 1 # clk $end
$var reg 1 $ en $end
$var reg 1 % rst_n $end
$var reg 1 & up $end
$scope module dut $end
$var wire 1 # clk $end
$var wire 1 $ en $end
$var wire 1 % rst_n $end
$var wire 1 & up $end
$var parameter 32 ' WIDTH $end
$var reg 4 ( q [3:0] $end
$upscope $end
$scope task step $end
$var integer 32 ) n [31:0] $end
$upscope $end
$upscope $end
$enddefinitions $end
$comment Show the parameter values. $end
$dumpall
b100 '
b100 "
$end
#0
$dumpvars
b1 )
bx (
1&
0%
0$
0#
bx !
$end
#5000
b0 !
b0 (
1%
1#
#10000
0#
#15000
b1 !
b1 (
b11 )
1$
0%
1#
#20000
0#
#25000
b10 !
b10 (
1#
#30000
0#
#35000
b11 !
b11 (
1#
#40000
0#
#45000
b10 !
b10 (
b10 )
0&
1#
#50000
0#
#55000
b1 !
b1 (
1#
#60000
0#
#65000
b11 )
0$
1#
