RISC-5 Single cycle/riscv_single/riscv_single/riscvsingle.sv
// riscvsingle.sv

// RISC-V single-cycle processor
// From Section 7.6 of Digital Design & Computer Architecture
// 27 April 2020
// David_Harris@hmc.edu 
// Sarah.Harris@unlv.edu

// run 210
// Expect simulator to print "Simulation succeeded"
// when the value 25 (0x19) is written to address 100 (0x64)

// Single-cycle implementation of RISC-V (RV32I)
// User-level Instruction Set Architecture V2.2 (May 7, 2017)
// Implements a subset of the base integer instructions:
//    lw, sw
//    add, sub, and, or, slt, 
//    addi, andi, ori, slti
//    beq
//    jal
// Exceptions, traps, and interrupts not implemented
// little-endian memory

// 31 32-bit registers x1-x31, x0 hardwired to 0
// R-Type instructions
//   add, sub, and, or, slt
//   INSTR rd, rs1, rs2
//   Instr[31:25] = funct7 (funct7b5 & opb5 = 1 for sub, 0 for others)
//   Instr[24:20] = rs2
//   Instr[19:15] = rs1
//   Instr[14:12] = funct3
//   Instr[11:7]  = rd
//   Instr[6:0]   = opcode
// I-Type Instructions
//   lw, I-type ALU (addi, andi, ori, slti)
//   lw:         INSTR rd, imm(rs1)
//   I-type ALU: INSTR rd, rs1, imm (12-bit signed)
//   Instr[31:20] = imm[11:0]
//   Instr[24:20] = rs2
//   Instr[19:15] = rs1
//   Instr[14:12] = funct3
//   Instr[11:7]  = rd
//   Instr[6:0]   = opcode
// S-Type Instruction
//   sw rs2, imm(rs1) (store rs2 into address specified by rs1 + immm)
//   Instr[31:25] = imm[11:5] (offset[11:5])
//   Instr[24:20] = rs2 (src)
//   Instr[19:15] = rs1 (base)
//   Instr[14:12] = funct3
//   Instr[11:7]  = imm[4:0]  (offset[4:0])
//   Instr[6:0]   = opcode
// B-Type Instruction
//   beq rs1, rs2, imm (PCTarget = PC + (signed imm x 2))
//   Instr[31:25] = imm[12], imm[10:5]
//   Instr[24:20] = rs2
//   Instr[19:15] = rs1
//   Instr[14:12] = funct3
//   Instr[11:7]  = imm[4:1], imm[11]
//   Instr[6:0]   = opcode
// J-Type Instruction
//   jal rd, imm  (signed imm is multiplied by 2 and added to PC, rd = PC+4)
//   Instr[31:12] = imm[20], imm[10:1], imm[11], imm[19:12]
//   Instr[11:7]  = rd
//   Instr[6:0]   = opcode

//   Instruction  opcode    funct3    funct7
//   add          0110011   000       0000000
//   sub          0110011   000       0100000
//   and          0110011   111       0000000
//   or           0110011   110       0000000
//   slt          0110011   010       0000000
//   addi         0010011   000       immediate
//   andi         0010011   111       immediate
//   ori          0010011   110       immediate
//   slti         0010011   010       immediate
//   beq          1100011   000       immediate
//   lw	          0000011   010       immediate
//   sw           0100011   010       immediate
//   jal          1101111   immediate immediate

module testbench();

  logic        clk;
  logic        reset;

  logic [31:0] WriteData, DataAdr;
  logic        MemWrite;

  // instantiate device to be tested
  top dut(clk, reset, WriteData, DataAdr, MemWrite);
  
  // initialize test
  initial
    begin
      $dumpfile("waves.vcd");
      $dumpvars(0, dut);
      reset <= 1; # 22; reset <= 0;
    end

  // generate clock to sequence tests
  always
    begin
      clk <= 1; # 5; clk <= 0; # 5;
    end

  // check results
  always @(negedge clk)
    begin
      if(MemWrite) begin
        if(DataAdr === 100 & WriteData === 25) begin
          $display("Simulation succeeded");
          $stop;
        end else if (DataAdr !== 96) begin
          $display("Simulation failed");
          $stop;
        end
      end
    end
    
endmodule

module top(input  logic        clk, reset, 
           output logic [31:0] WriteData, DataAdr, 
           output logic        MemWrite);

  logic [31:0] PC, Instr, ReadData;
  
  // instantiate processor and memories
  riscvsingle rvsingle(clk, reset, PC, Instr, MemWrite, DataAdr, 
                       WriteData, ReadData);
  imem imem(PC, Instr);
  dmem dmem(clk, MemWrite, DataAdr, WriteData, ReadData);
endmodule

module riscvsingle(input  logic        clk, reset,
                   output logic [31:0] PC,
                   input  logic [31:0] Instr,
                   output logic        MemWrite,
                   output logic [31:0] ALUResult, WriteData,
                   input  logic [31:0] ReadData);

  logic       ALUSrc, RegWrite, Jump, Zero;
  logic [1:0] ResultSrc, ImmSrc;
  logic [4:0] ALUControl;//1)Widen the ALU Bits from 3 bit to 5 bit.
                         //2)Then update the controller and aludec modules ports accordingly.

  controller c(Instr[6:0], Instr[14:12], Instr[31:25], Zero, //6) changing Instr[30] to Instr[31:25] since funct7 is 7 bits
               ResultSrc, MemWrite, PCSrc,
               ALUSrc, RegWrite, Jump,
               ImmSrc, ALUControl);
  datapath dp(clk, reset, ResultSrc, PCSrc,
              ALUSrc, RegWrite,
              ImmSrc, ALUControl,
              Zero, PC, Instr,
              ALUResult, WriteData, ReadData);
endmodule

module controller(input  logic [6:0] op,
                  input  logic [2:0] funct3,
                  input  logic [6:0] funct7, //4)Passing full bits for funct7 funct7b5 -> funct7
                  input  logic       Zero,
                  output logic [1:0] ResultSrc,
                  output logic       MemWrite,
                  output logic       PCSrc, ALUSrc,
                  output logic       RegWrite, Jump,
                  output logic [1:0] ImmSrc,
                  output logic [4:0] ALUControl); //3)Widen the output ALU bits also

  logic [1:0] ALUOp;
  logic       Branch;
  // logic       PCSrc;

  maindec md(op, ResultSrc, MemWrite, Branch,
             ALUSrc, RegWrite, Jump, ImmSrc, ALUOp);
  // aludec  ad(op, funct3, funct7, ALUOp, ALUControl); //5) Passing full bits for funct7 funct7b5 -> funct7
                //  input  logic       Zero,
  aludec  ad(funct7, funct3, ALUOp, ALUControl);

  assign PCSrc = Branch & Zero | Jump;
endmodule

module maindec(input  logic [6:0] op,
               output logic [1:0] ResultSrc,
               output logic       MemWrite,
               output logic       Branch, ALUSrc,
               output logic       RegWrite, Jump,
               output logic [1:0] ImmSrc,
               output logic [1:0] ALUOp);

  logic [10:0] controls;

  assign {RegWrite, ImmSrc, ALUSrc, MemWrite,
          ResultSrc, Branch, ALUOp, Jump} = controls;

  always_comb
    case(op)
    // RegWrite_ImmSrc_ALUSrc_MemWrite_ResultSrc_Branch_ALUOp_Jump
      7'b0000011: controls = 11'b1_00_1_0_01_0_00_0; // lw
      7'b0100011: controls = 11'b0_01_1_1_00_0_00_0; // sw
      7'b0110011: controls = 11'b1_xx_0_0_00_0_10_0; // R-type
      7'b0001011: controls = 11'b1_xx_0_0_00_0_11_0; // 8) RVX10 : Adding this new ALUOp '11'
      7'b1100011: controls = 11'b0_10_0_0_00_1_01_0; // beq
      7'b0010011: controls = 11'b1_00_1_0_00_0_10_0; // I-type ALU
      7'b1101111: controls = 11'b1_11_0_0_10_0_00_1; // jal
      default:    controls = 11'bx_xx_x_x_xx_x_xx_x; // non-implemented instruction
    endcase
endmodule

// We will modify the ALU to support the 
// module aludec(input  logic       opb5,
//               input  logic [2:0] funct3,
//               input  logic       funct7, //11) Wndening 3 bits to 5 bis
//               input  logic [1:0] ALUOp,
//               output logic [4:0] ALUControl); //9) Widening 3 bits to 5 bits
module aludec(input  logic [6:0] funct7, // Changed to a 7-bit input
              input  logic [2:0] funct3,
              input  logic [1:0] ALUOp,
              output logic [4:0] ALUControl);
  // logic  RtypeSub;
  // assign RtypeSub = funct7 & opb5;  // TRUE for R-type subtract instruction
  always_comb
    case(ALUOp) //10) INSTRUCTION DECODING FOR RVX10
        2'b00: ALUControl = 5'b00000; //Addition for ls/sw
      2'b01: ALUControl = 5'b00001; //Subtraction for beq
      2'b10: //R-type ot I-type ALU
        case(funct3)
          3'b000: if(funct7 == 7'b0100000) ALUControl = 5'b00001; //sub
                  else                     ALUControl = 5'b00000; //add , addi
          3'b010: ALUControl = 5'b00101; //slt, slti
          3'b110: ALUControl = 5'b00011; //or, ori
          3'b111: ALUControl = 5'b00010; //and,andi
          default:ALUControl = 5'bxxxxx; // ???
        endcase
      
      2'b11: //NEW : RVX10 Instructions
        case(funct7)
          7'b0000000: //ANDM, ORN , XNOR
            case(funct3)
              3'b000: ALUControl = 5'b01000; //ANDN
              3'b001: ALUControl = 5'b01001; //ORN
              3'b010: ALUControl = 5'b01010; //XNOR
              default:ALUControl = 5'bxxxxx; // ???
            endcase
          7'b0000001: //MIN,MAX,MINU,MAXU
            case(funct3)
              3'b000: ALUControl = 5'b01011; //MIN
              3'b001: ALUControl = 5'b01100; //MAX
              3'b010: ALUControl = 5'b01101; //MINU
              3'b011: ALUControl = 5'b01110; //MAXU
              default:ALUControl = 5'bxxxxx; // ???
            endcase

          7'b0000010: //ROL,ROR
            case(funct3)
              3'b000: ALUControl = 5'b01111; //ROL
              3'b001: ALUControl = 5'b10000; //ROR
              default:ALUControl = 5'bxxxxx; // ???

            endcase
          7'b0000011: //ABS
            case(funct3)
              3'b000: ALUControl = 5'b10001; //ABS
              default: ALUControl = 'bxxxxx; // ???
            endcase
          default: ALUControl = 5'bxxxxx; // ???
        endcase
        default: ALUControl = 5'bxxxxx; // ???
    endcase

endmodule

module datapath(input  logic        clk, reset,
                input  logic [1:0]  ResultSrc, 
                input  logic        PCSrc, ALUSrc,
                input  logic        RegWrite,
                input  logic [1:0]  ImmSrc,
                input  logic [4:0]  ALUControl, //7) Updating the ALUControl bits from 3 to 5 bits
                output logic        Zero,
                output logic [31:0] PC,
                input  logic [31:0] Instr,
                output logic [31:0] ALUResult, WriteData,
                input  logic [31:0] ReadData);

  logic [31:0] PCNext, PCPlus4, PCTarget;
  logic [31:0] ImmExt;
  logic [31:0] SrcA, SrcB;
  logic [31:0] Result;

  // next PC logic
  flopr #(32) pcreg(clk, reset, PCNext, PC); 
  adder       pcadd4(PC, 32'd4, PCPlus4);
  adder       pcaddbranch(PC, ImmExt, PCTarget);
  mux2 #(32)  pcmux(PCPlus4, PCTarget, PCSrc, PCNext);
 
  // register file logic
  regfile     rf(clk, RegWrite, Instr[19:15], Instr[24:20], 
                 Instr[11:7], Result, SrcA, WriteData);
  extend      ext(Instr[31:7], ImmSrc, ImmExt);

  // ALU logic
  mux2 #(32)  srcbmux(WriteData, ImmExt, ALUSrc, SrcB);
  alu         alu(SrcA, SrcB, ALUControl, ALUResult, Zero);
  mux3 #(32)  resultmux(ALUResult, ReadData, PCPlus4, ResultSrc, Result);
endmodule

module regfile(input  logic        clk, 
               input  logic        we3, 
               input  logic [ 4:0] a1, a2, a3, 
               input  logic [31:0] wd3, 
               output logic [31:0] rd1, rd2);

  logic [31:0] rf[31:0];

  // three ported register file
  // read two ports combinationally (A1/RD1, A2/RD2)
  // write third port on rising edge of clock (A3/WD3/WE3)
  // register 0 hardwired to 0

  always_ff @(posedge clk)
    if (we3) rf[a3] <= wd3;	

  assign rd1 = (a1 != 0) ? rf[a1] : 0;
  assign rd2 = (a2 != 0) ? rf[a2] : 0;
endmodule

module adder(input  [31:0] a, b,
             output [31:0] y);

  assign y = a + b;
endmodule

module extend(input  logic [31:7] instr,
              input  logic [1:0]  immsrc,
              output logic [31:0] immext);

  // This logic is the same as the case statement but written in a way
  // that avoids the iverilog "constant selects" issue.
  assign immext =
    (immsrc == 2'b00) ? {{20{instr[31]}}, instr[31:20]} :                           // I-type
    (immsrc == 2'b01) ? {{20{instr[31]}}, instr[31:25], instr[11:7]} :              // S-type
    (immsrc == 2'b10) ? {{20{instr[31]}}, instr[7], instr[30:25], instr[11:8], 1'b0} : // B-type
    (immsrc == 2'b11) ? {{12{instr[31]}}, instr[19:12], instr[20], instr[30:21], 1'b0} : // J-type
    32'bx; // Default case

endmodule
// module extend(input  logic [31:7] instr,
//               input  logic [1:0]  immsrc,
//               output logic [31:0] immext);
 
//   always_comb
//     case(immsrc) 
//                // I-type 
//       2'b00:   immext = {{20{instr[31]}}, instr[31:20]};  
//                // S-type (stores)
//       2'b01:   immext = {{20{instr[31]}}, instr[31:25], instr[11:7]}; 
//                // B-type (branches)
//       2'b10:   immext = {{20{instr[31]}}, instr[7], instr[30:25], instr[11:8], 1'b0}; 
//                // J-type (jal)
//       2'b11:   immext = {{12{instr[31]}}, instr[19:12], instr[20], instr[30:21], 1'b0}; 
//       default: immext = 32'bx; // undefined
//     endcase             
// endmodule

module flopr #(parameter WIDTH = 8)
              (input  logic             clk, reset,
               input  logic [WIDTH-1:0] d, 
               output logic [WIDTH-1:0] q);

  always_ff @(posedge clk, posedge reset)
    if (reset) q <= 0;
    else       q <= d;
endmodule

module mux2 #(parameter WIDTH = 8)
             (input  logic [WIDTH-1:0] d0, d1, 
              input  logic             s, 
              output logic [WIDTH-1:0] y);

  assign y = s ? d1 : d0; 
endmodule

module mux3 #(parameter WIDTH = 8)
             (input  logic [WIDTH-1:0] d0, d1, d2,
              input  logic [1:0]       s, 
              output logic [WIDTH-1:0] y);

  assign y = s[1] ? d2 : (s[0] ? d1 : d0); 
endmodule

module imem(input  logic [31:0] a,
            output logic [31:0] rd);

  logic [31:0] RAM[63:0];

  initial
      $readmemh("riscvtest.txt",RAM);

  assign rd = RAM[a[31:2]]; // word aligned
endmodule

module dmem(input  logic        clk, we,
            input  logic [31:0] a, wd,
            output logic [31:0] rd);

  logic [31:0] RAM[63:0];

  assign rd = RAM[a[31:2]]; // word aligned

  always_ff @(posedge clk)
    if (we) RAM[a[31:2]] <= wd;
endmodule

// module alu(input  logic [31:0] a, b,
//            input  logic [4:0]  alucontrol, //widen the bits from 3 to 5 bits
//            output logic [31:0] result,
//            output logic        zero);

//   logic [31:0] condinvb, sum;
//   logic        v;              // overflow
//   logic        isAddSub;       // true when is add or subtract operation

//   assign condinvb = alucontrol[0] ? ~b : b;
//   assign sum = a + condinvb + alucontrol[0];
//   assign isAddSub = ~alucontrol[2] & ~alucontrol[1] |
//                     ~alucontrol[1] & alucontrol[0];

//   always_comb 
  
//     case (alucontrol)
//       5'b00000:  result = sum;         // add
//       5'b00001:  result = sum;         // subtract
//       5'b00010:  result = a & b;       // and
//       5'b00011:  result = a | b;       // or
//       5'b00100:  result = a ^ b;       // xor
//       5'b00101:  result = sum[31] ^ v; // slt
//       5'b00110:  result = a << b[4:0]; // sll
//       5'b00111:  result = a >> b[4:0]; // srl


//     //New RVX10 Operations
//       5'b01000: result = a & ~b;        // ANDN
//       5'b01001: result = a | ~b;        //ORN
//       5'b01010: result = ~(a^b);        //XNOR
//       5'b01011: result = ($signed(a) < $signed(b)) ? a : b; //MIN
//       5'b01100: result = ($signed(a) > $signed(b)) ? a : b; //MAX
//       5'b01101: result = (a < b) ? a : b; //MINU
//       5'b01110: result = (a > b) ? a : b; //MAXU
//       5'b01111: result = (b[4:0] == 0) ? a:(a<<b[4:0]) | (a>>(32 - b[4:0])); //ROL
//       5'b10000: result = (b[4:0] == 0) ? a:(a>>b[4:0]) | (a<<(32 - b[4:0])); //ROR
//       5'b10001: result = ($signed(a) >= 0) ? a:-a; //ABS 

//       default: result = 32'bx;
//     endcase

//   assign zero = (result == 32'b0);
//   assign v = ~(alucontrol[0] ^ a[31] ^ b[31]) & (a[31] ^ sum[31]) & isAddSub;
  
// endmodule
module alu(input  logic [31:0] a, b,
           input  logic [4:0]  alucontrol,
           output logic [31:0] result,
           output logic        zero);

    always_comb
      begin
        // Create a local variable for the shift amount to make the logic
        // explicit and avoid simulator warnings.
        logic [4:0] shamt = b[4:0];
        
        case (alucontrol)
          // Standard ALU operations (simplified for clarity and compatibility)
          5'b00000: result = a + b;
          5'b00001: result = a - b;
          5'b00010: result = a & b;
          5'b00011: result = a | b;
          5'b00100: result = a ^ b;
          5'b00101: result = ($signed(a) < $signed(b)) ? 32'd1 : 32'd0; // slt
          5'b00110: result = a << shamt;                                 // sll
          5'b00111: result = a >> shamt;                                 // srl

          // New RVX10 Operations
          5'b01000: result = a & ~b;
          5'b01001: result = a | ~b;
          5'b01010: result = ~(a ^ b);
          5'b01011: result = ($signed(a) < $signed(b)) ? a : b;
          5'b01100: result = ($signed(a) > $signed(b)) ? a : b;
          5'b01101: result = (a < b) ? a : b;
          5'b01110: result = (a > b) ? a : b;
          5'b01111: result = (shamt == 0) ? a : (a << shamt) | (a >> (32 - shamt));
          5'b10000: result = (shamt == 0) ? a : (a >> shamt) | (a << (32 - shamt));
          5'b10001: result = ($signed(a) >= 0) ? a : -a;
          
          default: result = 32'bx;
        endcase
      end
      
    assign zero = (result == 32'b0);
  
endmodule

RISC-5 Single cycle/riscv_single/riscv_single/riscvsingle.vcd
$date
	Wed Oct  8 13:23:48 2025
$end
$version
	Icarus Verilog
$end
$timescale
	1s
$end
$scope module testbench $end
$scope module dut $end
$var wire 1 ! clk $end
$var wire 1 " reset $end
$var wire 32 # WriteData [31:0] $end
$var wire 32 $ ReadData [31:0] $end
$var wire 32 % PC [31:0] $end
$var wire 1 & MemWrite $end
$var wire 32 ' Instr [31:0] $end
$var wire 32 ( DataAdr [31:0] $end
$scope module dmem $end
$var wire 1 ! clk $end
$var wire 32 ) rd [31:0] $end
$var wire 1 & we $end
$var wire 32 * wd [31:0] $end
$var wire 32 + a [31:0] $end
$upscope $end
$scope module imem $end
$var wire 32 , rd [31:0] $end
$var wire 32 - a [31:0] $end
$upscope $end
$scope module rvsingle $end
$var wire 32 . Instr [31:0] $end
$var wire 32 / ReadData [31:0] $end
$var wire 1 ! clk $end
$var wire 1 " reset $end
$var wire 1 0 Zero $end
$var wire 32 1 WriteData [31:0] $end
$var wire 2 2 ResultSrc [1:0] $end
$var wire 1 3 RegWrite $end
$var wire 1 4 PCSrc $end
$var wire 32 5 PC [31:0] $end
$var wire 1 & MemWrite $end
$var wire 1 6 Jump $end
$var wire 2 7 ImmSrc [1:0] $end
$var wire 1 8 ALUSrc $end
$var wire 32 9 ALUResult [31:0] $end
$var wire 5 : ALUControl [4:0] $end
$scope module c $end
$var wire 1 4 PCSrc $end
$var wire 3 ; funct3 [2:0] $end
$var wire 7 < funct7 [6:0] $end
$var wire 7 = op [6:0] $end
$var wire 1 0 Zero $end
$var wire 2 > ResultSrc [1:0] $end
$var wire 1 3 RegWrite $end
$var wire 1 & MemWrite $end
$var wire 1 6 Jump $end
$var wire 2 ? ImmSrc [1:0] $end
$var wire 1 @ Branch $end
$var wire 1 8 ALUSrc $end
$var wire 2 A ALUOp [1:0] $end
$var wire 5 B ALUControl [4:0] $end
$scope module ad $end
$var wire 3 C funct3 [2:0] $end
$var wire 7 D funct7 [6:0] $end
$var wire 2 E ALUOp [1:0] $end
$var reg 5 F ALUControl [4:0] $end
$upscope $end
$scope module md $end
$var wire 7 G op [6:0] $end
$var wire 2 H ResultSrc [1:0] $end
$var wire 1 3 RegWrite $end
$var wire 1 & MemWrite $end
$var wire 1 6 Jump $end
$var wire 2 I ImmSrc [1:0] $end
$var wire 1 @ Branch $end
$var wire 1 8 ALUSrc $end
$var wire 2 J ALUOp [1:0] $end
$var reg 11 K controls [10:0] $end
$upscope $end
$upscope $end
$scope module dp $end
$var wire 5 L ALUControl [4:0] $end
$var wire 1 8 ALUSrc $end
$var wire 2 M ImmSrc [1:0] $end
$var wire 32 N Instr [31:0] $end
$var wire 1 4 PCSrc $end
$var wire 32 O ReadData [31:0] $end
$var wire 1 3 RegWrite $end
$var wire 2 P ResultSrc [1:0] $end
$var wire 1 ! clk $end
$var wire 1 " reset $end
$var wire 1 0 Zero $end
$var wire 32 Q WriteData [31:0] $end
$var wire 32 R SrcB [31:0] $end
$var wire 32 S SrcA [31:0] $end
$var wire 32 T Result [31:0] $end
$var wire 32 U PCTarget [31:0] $end
$var wire 32 V PCPlus4 [31:0] $end
$var wire 32 W PCNext [31:0] $end
$var wire 32 X PC [31:0] $end
$var wire 32 Y ImmExt [31:0] $end
$var wire 32 Z ALUResult [31:0] $end
$scope module alu $end
$var wire 5 [ alucontrol [4:0] $end
$var wire 1 0 zero $end
$var wire 32 \ b [31:0] $end
$var wire 32 ] a [31:0] $end
$var reg 32 ^ result [31:0] $end
$scope begin $unm_blk_7 $end
$var reg 5 _ shamt [4:0] $end
$upscope $end
$upscope $end
$scope module ext $end
$var wire 2 ` immsrc [1:0] $end
$var wire 25 a instr [31:7] $end
$var wire 32 b immext [31:0] $end
$upscope $end
$scope module pcadd4 $end
$var wire 32 c b [31:0] $end
$var wire 32 d y [31:0] $end
$var wire 32 e a [31:0] $end
$upscope $end
$scope module pcaddbranch $end
$var wire 32 f b [31:0] $end
$var wire 32 g y [31:0] $end
$var wire 32 h a [31:0] $end
$upscope $end
$scope module pcmux $end
$var wire 32 i d0 [31:0] $end
$var wire 32 j d1 [31:0] $end
$var wire 1 4 s $end
$var wire 32 k y [31:0] $end
$var parameter 32 l WIDTH $end
$upscope $end
$scope module pcreg $end
$var wire 1 ! clk $end
$var wire 32 m d [31:0] $end
$var wire 1 " reset $end
$var parameter 32 n WIDTH $end
$var reg 32 o q [31:0] $end
$upscope $end
$scope module resultmux $end
$var wire 32 p d0 [31:0] $end
$var wire 32 q d1 [31:0] $end
$var wire 32 r d2 [31:0] $end
$var wire 2 s s [1:0] $end
$var wire 32 t y [31:0] $end
$var parameter 32 u WIDTH $end
$upscope $end
$scope module rf $end
$var wire 5 v a1 [4:0] $end
$var wire 5 w a2 [4:0] $end
$var wire 5 x a3 [4:0] $end
$var wire 1 ! clk $end
$var wire 32 y wd3 [31:0] $end
$var wire 1 3 we3 $end
$var wire 32 z rd2 [31:0] $end
$var wire 32 { rd1 [31:0] $end
$upscope $end
$scope module srcbmux $end
$var wire 32 | d0 [31:0] $end
$var wire 32 } d1 [31:0] $end
$var wire 1 8 s $end
$var wire 32 ~ y [31:0] $end
$var parameter 32 !" WIDTH $end
$upscope $end
$upscope $end
$upscope $end
$upscope $end
$upscope $end
$enddefinitions $end
$comment Show the parameter values. $end
$dumpall
b100000 !"
b100000 u
b100000 n
b100000 l
$end
#0
$dumpvars
b101 ~
b101 }
bx |
b0 {
bx z
b101 y
b10 x
b101 w
b0 v
b101 t
b0 s
b100 r
bx q
b101 p
b0 o
b100 m
b100 k
b101 j
b100 i
b0 h
b101 g
b101 f
b0 e
b100 d
b100 c
b101 b
b1010000000000010 a
b0 `
bz _
b101 ^
b0 ]
b101 \
b0 [
b101 Z
b101 Y
b0 X
b100 W
b100 V
b101 U
b101 T
b0 S
b101 R
bx Q
b0 P
bx O
b10100000000000100010011 N
b0 M
b0 L
b10010000100 K
b10 J
b0 I
b0 H
b10011 G
b0 F
b10 E
b0 D
b0 C
b0 B
b10 A
0@
b0 ?
b0 >
b10011 =
b0 <
b0 ;
b0 :
b101 9
18
b0 7
06
b0 5
04
13
b0 2
bx 1
00
bx /
b10100000000000100010011 .
b0 -
b10100000000000100010011 ,
b101 +
bx *
bx )
b101 (
b10100000000000100010011 '
0&
b0 %
bx $
bx #
1"
1!
$end
#5
0!
#10
1!
#15
0!
#20
1!
#22
0"
#25
0!
#30
b1100 T
b1100 t
b1100 y
b1100 (
b1100 +
b1100 9
b1100 Z
b1100 ^
b1100 p
b1100 R
b1100 \
b1100 ~
b1100 Y
b1100 b
b1100 f
b1100 }
b1100 w
b11 x
b11000000000000011 a
b1000 W
b1000 k
b1000 m
b110000000000000110010011 '
b110000000000000110010011 ,
b110000000000000110010011 .
b110000000000000110010011 N
b10000 U
b10000 g
b10000 j
b1000 V
b1000 d
b1000 i
b1000 r
b100 %
b100 -
b100 5
b100 X
b100 e
b100 h
b100 o
1!
#35
0!
#40
b11 T
b11 t
b11 y
b11111111111111111111111111110111 R
b11111111111111111111111111110111 \
b11111111111111111111111111110111 ~
b11 (
b11 +
b11 9
b11 Z
b11 ^
b11 p
b11111111111111111111111111110111 Y
b11111111111111111111111111110111 b
b11111111111111111111111111110111 f
b11111111111111111111111111110111 }
b1100 S
b1100 ]
b1100 {
b1111111 <
b1111111 D
b11 v
b10111 w
b111 x
b1111111101110001100000111 a
b1100 W
b1100 k
b1100 m
b11111111011100011000001110010011 '
b11111111011100011000001110010011 ,
b11111111011100011000001110010011 .
b11111111011100011000001110010011 N
b11111111111111111111111111111111 U
b11111111111111111111111111111111 g
b11111111111111111111111111111111 j
b1100 V
b1100 d
b1100 i
b1100 r
b1000 %
b1000 -
b1000 5
b1000 X
b1000 e
b1000 h
b1000 o
1!
#45
0!
#50
b111 T
b111 t
b111 y
b101 R
b101 \
b101 ~
bx 7
bx ?
bx I
bx M
bx `
08
b111 (
b111 +
b111 9
b111 Z
b111 ^
b111 p
bx Y
bx b
bx f
bx }
b1xx00000100 K
b11 :
b11 B
b11 F
b11 L
b11 [
b11 S
b11 ]
b11 {
b101 #
b101 *
b101 1
b101 Q
b101 z
b101 |
b110011 =
b110011 G
b110 ;
b110 C
b0 <
b0 D
b111 v
b10 w
b100 x
b100011111000100 a
b10000 W
b10000 k
b10000 m
b1000111110001000110011 '
b1000111110001000110011 ,
b1000111110001000110011 .
b1000111110001000110011 N
bx U
bx g
bx j
b10000 V
b10000 d
b10000 i
b10000 r
b1100 %
b1100 -
b1100 5
b1100 X
b1100 e
b1100 h
b1100 o
1!
#55
0!
#60
b100 T
b100 t
b100 y
b100 (
b100 +
b100 9
b100 Z
b100 ^
b100 p
b111 R
b111 \
b111 ~
b10 :
b10 B
b10 F
b10 L
b10 [
b1100 S
b1100 ]
b1100 {
b111 #
b111 *
b111 1
b111 Q
b111 z
b111 |
b111 ;
b111 C
b11 v
b100 w
b101 x
b1000001111100101 a
b10100 W
b10100 k
b10100 m
b10000011111001010110011 '
b10000011111001010110011 ,
b10000011111001010110011 .
b10000011111001010110011 N
b10100 V
b10100 d
b10100 i
b10100 r
b10000 %
b10000 -
b10000 5
b10000 X
b10000 e
b10000 h
b10000 o
1!
#65
0!
#70
b1011 T
b1011 t
b1011 y
b1011 (
b1011 +
b1011 9
b1011 Z
b1011 ^
b1011 p
b0 :
b0 B
b0 F
b0 L
b0 [
b100 S
b100 ]
b100 {
b0 ;
b0 C
b101 v
b1000010100000101 a
b11000 W
b11000 k
b11000 m
b10000101000001010110011 '
b10000101000001010110011 ,
b10000101000001010110011 .
b10000101000001010110011 N
b11000 V
b11000 d
b11000 i
b11000 r
b10100 %
b10100 -
b10100 5
b10100 X
b10100 e
b10100 h
b10100 o
1!
#75
0!
#80
b1001000 U
b1001000 g
b1001000 j
b110000 Y
b110000 b
b110000 f
b110000 }
b1 :
b1 B
b1 F
b1 L
b1 [
b1000 T
b1000 t
b1000 y
03
b10 7
b10 ?
b10 I
b10 M
b10 `
1@
b1 A
b1 E
b1 J
b11 R
b11 \
b11 ~
b1000001010 K
b11 #
b11 *
b11 1
b11 Q
b11 z
b11 |
b1000 (
b1000 +
b1000 9
b1000 Z
b1000 ^
b1000 p
b1100011 =
b1100011 G
b1 <
b1 D
b111 w
b10000 x
b1001110010100010000 a
b1011 S
b1011 ]
b1011 {
b11100 W
b11100 k
b11100 m
b10011100101000100001100011 '
b10011100101000100001100011 ,
b10011100101000100001100011 .
b10011100101000100001100011 N
b11100 V
b11100 d
b11100 i
b11100 r
b11000 %
b11000 -
b11000 5
b11000 X
b11000 e
b11000 h
b11000 o
1!
#85
0!
#90
10
b0 T
b0 t
b0 y
bx Y
bx b
bx f
bx }
b101 :
b101 B
b101 F
b101 L
b101 [
13
bx 7
bx ?
bx I
bx M
bx `
0@
b10 A
b10 E
b10 J
b0 (
b0 +
b0 9
b0 Z
b0 ^
b0 p
b111 R
b111 \
b111 ~
b1xx00000100 K
b1100 S
b1100 ]
b1100 {
b111 #
b111 *
b111 1
b111 Q
b111 z
b111 |
b110011 =
b110011 G
b10 ;
b10 C
b0 <
b0 D
b11 v
b100 w
b100 x
b1000001101000100 a
b100000 W
b100000 k
b100000 m
b10000011010001000110011 '
b10000011010001000110011 ,
b10000011010001000110011 .
b10000011010001000110011 N
bx U
bx g
bx j
b100000 V
b100000 d
b100000 i
b100000 r
b11100 %
b11100 -
b11100 5
b11100 X
b11100 e
b11100 h
b11100 o
1!
#95
0!
#100
14
b101000 U
b101000 g
b101000 j
b1000 Y
b1000 b
b1000 f
b1000 }
03
b10 7
b10 ?
b10 I
b10 M
b10 `
1@
b1 A
b1 E
b1 J
b1000001010 K
b1 :
b1 B
b1 F
b1 L
b1 [
b0 S
b0 ]
b0 {
b0 R
b0 \
b0 ~
b1100011 =
b1100011 G
b0 ;
b0 C
b100 v
b0 w
b1000 x
b10000001000 a
b0 #
b0 *
b0 1
b0 Q
b0 z
b0 |
b101000 W
b101000 k
b101000 m
b100000010001100011 '
b100000010001100011 ,
b100000010001100011 .
b100000010001100011 N
b100100 V
b100100 d
b100100 i
b100100 r
b100000 %
b100000 -
b100000 5
b100000 X
b100000 e
b100000 h
b100000 o
1!
#105
0!
#110
04
b1 T
b1 t
b1 y
bx Y
bx b
bx f
bx }
b101 :
b101 B
b101 F
b101 L
b101 [
13
bx 7
bx ?
bx I
bx M
bx `
0@
b10 A
b10 E
b10 J
00
b1 (
b1 +
b1 9
b1 Z
b1 ^
b1 p
b101 R
b101 \
b101 ~
b1xx00000100 K
b11 S
b11 ]
b11 {
b101 #
b101 *
b101 1
b101 Q
b101 z
b101 |
b110011 =
b110011 G
b10 ;
b10 C
b111 v
b10 w
b100 x
b100011101000100 a
b101100 W
b101100 k
b101100 m
b1000111010001000110011 '
b1000111010001000110011 ,
b1000111010001000110011 .
b1000111010001000110011 N
bx U
bx g
bx j
b101100 V
b101100 d
b101100 i
b101100 r
b101000 %
b101000 -
b101000 5
b101000 X
b101000 e
b101000 h
b101000 o
1!
#115
0!
#120
b1100 T
b1100 t
b1100 y
b1100 (
b1100 +
b1100 9
b1100 Z
b1100 ^
b1100 p
b1011 R
b1011 \
b1011 ~
b0 :
b0 B
b0 F
b0 L
b0 [
b1 S
b1 ]
b1 {
b1011 #
b1011 *
b1011 1
b1011 Q
b1011 z
b1011 |
b0 ;
b0 C
b100 v
b101 w
b111 x
b1010010000000111 a
b110000 W
b110000 k
b110000 m
b10100100000001110110011 '
b10100100000001110110011 ,
b10100100000001110110011 .
b10100100000001110110011 N
b110000 V
b110000 d
b110000 i
b110000 r
b101100 %
b101100 -
b101100 5
b101100 X
b101100 e
b101100 h
b101100 o
1!
#125
0!
