fsm_assignment/problem1_seq_det/seq_detect_mealy.v
//Goal: Detect serial bit pattern 1101 on din with overlap. Output y is a 1-cycle pulse when the
// last bit arrives.
// Type: Mealy Reset: synchronous, active-high.

module seq_detector(
    input wire clk,
    input wire rst,
    input wire din,
    output reg y
);

// implementation of the state machine
// Define states :- 

parameter S0 = 2'b00;
parameter S1 = 2'b01;
parameter S2 = 2'b10;
parameter S3 = 2'b11;

reg[1:0] current_state,next_state;


// reset block
always @(*) begin
    if(rst)
    current_state  = S0;
    else
    current_state <=next_state;
end


//combinational logic
always @(posedge clk)begin
    next_state = current_state; // default to current state
    y = 1'b0; // default output


    case(current_state)
        S0: begin
            if(din) next_state = S1; // i/p = 1
            else next_state = S0; // i/p = 0
        end
        S1: begin
            if(din) next_state = S2; // total i/p = 11
            else next_state = S0; // total i/p = 10
        end
        S2: begin
            if(din) next_state = S2; // total i/p = 110
            else next_state = S3; // total i/p = 111
        end
        S3: begin
            if(din) begin
                y <= 1'b1; // total i/p = 1101 detected
                next_state = S1; // overlap, go back to state S1 for the next bit
            end 
            else begin
                y <= 0; // no pulse if din is not 1 after detecting 1101
                next_state = S0; // reset to state S0 if din is not 1
            end
        end
        default: begin
            next_state = S0; // default case to handle unexpected states
        end
    endcase
end


endmodule

fsm_assignment/problem1_seq_det/tb_seq_detect_mealy.v
`timescale 1ns/1ns
`include "seq_detect_mealy.v"

module tb_seq_detector;

    reg clk, rst, din;
    wire y;

    // DUT instance
    seq_detector dut (
        .clk(clk),
        .rst(rst),
        .din(din),
        .y(y)
    );

    // Clock generation: period = 10
    initial clk = 0;
    always #5 clk = ~clk;

    // Stimulus
    initial begin 
        $dumpfile("seq_detector_vcd_file.vcd");
        $dumpvars(0, tb_seq_detector);

        // Apply reset
        rst = 1; 
        din = 0;
        #10;         // keep reset active for 1 clock cycle
        rst = 0; 

        // Drive inputs: 1101 should trigger detection
        din = 1; #10;
        din = 1; #10;
        din = 0; #10;
        din = 1; #10;  // <-- sequence 1101 detected here

        // Extra inputs
        din = 0; #10;
        din = 1; #10;
        din = 1; #10;
        din = 0; #10;
        din = 1; #10;

        $display("Test completed!");
        $finish;
    end

    // Monitor signals
    initial begin
        $display("Time\tclk\trst\tdin\ty");
        $monitor("%0t\t%b\t%b\t%b\t%b", $time, clk, rst, din, y);
    end

endmodule

fsm_assignment/problem1_seq_det/wave/seq_detect_vcd_file.vcd
$date
	Mon Aug 18 19:19:20 2025
$end
$version
	Icarus Verilog
$end
$timescale
	1ns
$end
$scope module tb_seq_detector $end
$var wire 1 ! y $end
$var reg 1 " clk $end
$var reg 1 # din $end
$var reg 1 $ rst $end
$scope module dut $end
$var wire 1 " clk $end
$var wire 1 # din $end
$var wire 1 $ rst $end
$var parameter 2 % S0 $end
$var parameter 2 & S1 $end
$var parameter 2 ' S2 $end
$var parameter 2 ( S3 $end
$var reg 2 ) current_state [1:0] $end
$var reg 2 * next_state [1:0] $end
$var reg 1 ! y $end
$upscope $end
$upscope $end
$enddefinitions $end
$comment Show the parameter values. $end
$dumpall
b11 (
b10 '
b1 &
b0 %
$end
#0
$dumpvars
bx *
b0 )
1$
0#
0"
x!
$end
#5
0!
b0 *
1"
#10
0"
1#
0$
#15
b1 )
b1 *
1"
#20
0"
#25
b10 )
b10 *
1"
#30
0"
0#
#35
b11 )
b11 *
1"
#40
0"
1#
#45
b1 )
1!
b1 *
1"
#50
0"
0#
#55
b0 )
b0 *
0!
1"
#60
0"
1#
#65
b1 )
b1 *
1"
#70
0"
#75
b10 )
b10 *
1"
#80
0"
0#
#85
b11 )
b11 *
1"
#90
0"
1#
#95
b1 )
1!
b1 *
1"
