Practice/MUX/mux2.sv
`timescale 1ns/1ps
// `default_nettype none
module mux2(
    input logic a , b , sel,
    output logic y
);

always_comb begin
    y = sel ? b:a;
end

endmodule

// `default_nettype wire

Practice/MUX/tb_mux2.sv
`timescale 1ns/1ps
// `dafault_nettype none

module tb_mux2;
logic a,b,sel,y;

mux2 dut(.a(a),.b(b),.sel(sel),.y(y));

initial begin 
    $dumpfile("mux2.vcd");
    $dumpvars(0,tb_mux2);

    a=0;b=1;sel=0; #1;
    assert(y==a) else $fatal(1, "sel=0 expected y=a");

    sel=1; #1;
    assert(y==b) else $fatal(1, "sel=1 expected y=b");

    repeat(8) begin
        a= $urandom_range(0,1);
        b= $urandom_range(0,1);
        sel= $urandom_range(0,1); #1;

        assert(y==(sel?b:a)) else $fatal(1,"mismatch rand");
    end

    $display("[MUX2] ALL TESTS PASSED,");
    $finish;
end
endmodule

// `default_nettype wire

Practice/MUX/mux2.vcd
$date
	Fri Sep 26 05:14:44 2025
$end
$version
	Icarus Verilog
$end
$timescale
	1ps
$end
$scope module tb_mux2 $end
$var wire 1 ! y $end
$var reg 1 " a $end
$var reg 1 # b $end
$var reg 1 $ sel $end
$scope module dut $end
$var wire 1 " a $end
$var wire 1 # b $end
$var wire 1 $ sel $end
$var reg 1 ! y $end
$upscope $end
$upscope $end
$enddefinitions $end
$comment Show the parameter values. $end
$dumpall
$end
#0
$dumpvars
0$
1#
0"
0!
$end
#1000
1!
1$
#2000
0$
0#
1"
#3000
1$
1#
0"
#4000
0!
0#
#5000
1!
1#
1"
#7000
0!
0$
0#
0"
#8000
1!
1"
#9000
1#
