fsm_assignment/problem4_link/slave_fsm.v
module slave_fsm(
    input wire clk,
    input wire rst,
    input wire req,
    input wire [7:0] data_in,
    output reg ack,
    output reg [7:0] last_byte
);

    reg [2:0] state, next_state;

    localparam IDLE        = 3'd0,
               LATCH       = 3'd1,
               HOLD1       = 3'd2,
               HOLD2       = 3'd3,
               WAIT_REQ_LOW= 3'd4;

    // State register
    always @(posedge clk or posedge rst) begin
        if (rst) state <= IDLE;
        else state <= next_state;
    end

    // Next state logic
    always @(*) begin
        next_state = state;
        case (state)
            IDLE:        if (req) next_state = LATCH;
            LATCH:       next_state = HOLD1;
            HOLD1:       next_state = HOLD2;
            HOLD2:       next_state = WAIT_REQ_LOW;
            WAIT_REQ_LOW:if (!req) next_state = IDLE;
        endcase
    end

    // Output logic
    always @(posedge clk or posedge rst) begin
        if (rst) begin
            ack <= 0; last_byte <= 0;
        end else begin
            case (next_state)
                LATCH: begin
                    last_byte <= data_in;
                    ack <= 1;
                end
                HOLD1, HOLD2: ack <= 1;
                WAIT_REQ_LOW: if (!req) ack <= 0;
            endcase
        end
    end

endmodule

fsm_assignment/problem4_link/master_fsm.v
module master_fsm(
    input wire clk,
    input wire rst,
    input wire ack,
    output reg req,
    output reg [7:0] data,
    output reg done
);

    reg [2:0] state, next_state;
    reg [1:0] byte_cnt;

    localparam IDLE        = 3'd0,
               SEND_REQ    = 3'd1,
               WAIT_ACK    = 3'd2,
               DROP_REQ    = 3'd3,
               WAIT_ACK_LOW= 3'd4,
               CHECK_COUNT = 3'd5,
               DONE_STATE  = 3'd6;

    // State register
    always @(posedge clk or posedge rst) begin
        if (rst) begin
            state <= IDLE;
            byte_cnt <= 0;
        end else begin
            state <= next_state;
            if (state == CHECK_COUNT && ack == 0 && byte_cnt < 3)
                byte_cnt <= byte_cnt + 1;
        end
    end

    // Next-state logic
    always @(*) begin
        next_state = state;
        case (state)
            IDLE:        next_state = SEND_REQ;
            SEND_REQ:    next_state = WAIT_ACK;
            WAIT_ACK:    if (ack) next_state = DROP_REQ;
            DROP_REQ:    next_state = WAIT_ACK_LOW;
            WAIT_ACK_LOW:if (!ack) next_state = CHECK_COUNT;
            CHECK_COUNT: if (byte_cnt == 3) next_state = DONE_STATE;
                         else next_state = SEND_REQ;
            DONE_STATE:  next_state = DONE_STATE;
        endcase
    end

    // Output logic
    always @(posedge clk or posedge rst) begin
        if (rst) begin
            req <= 0; data <= 0; done <= 0;
        end else begin
            case (next_state)
                SEND_REQ: begin
                    req <= 1;
                    data <= byte_cnt; // test: send 0,1,2,3
                    done <= 0;
                end
                DROP_REQ: req <= 0;
                DONE_STATE: done <= 1;
                default: done <= 0;
            endcase
        end
    end

endmodule

fsm_assignment/problem4_link/link_top.v
`include "master_fsm.v"
`include "slave_fsm.v"

module link_top(
    input wire clk,
    input wire rst,
    output wire done
);

    wire req, ack;
    wire [7:0] data;
    wire [7:0] last_byte;

    master_fsm u_master(
        .clk(clk), .rst(rst),
        .ack(ack), .req(req),
        .data(data), .done(done)
    );

    slave_fsm u_slave(
        .clk(clk), .rst(rst),
        .req(req), .data_in(data),
        .ack(ack), .last_byte(last_byte)
    );

endmodule

fsm_assignment/problem4_link/tb_link_top.v
`timescale 1ns/1ps
`include "link_top.v"
module tb_link_top;

    reg clk, rst;
    wire done;

    link_top dut(.clk(clk), .rst(rst), .done(done));

    // Clock
    always #5 clk = ~clk;

    initial begin
        $dumpfile("master_slave.vcd");
        $dumpvars(0, tb_link_top);

        clk = 0;
        rst = 1;
        #15 rst = 0;   // release reset

        wait(done);
        #20;
        $finish;
    end

endmodule

fsm_assignment/problem4_link/waves/master_slave.vcd
$date
	Tue Aug 19 17:06:54 2025
$end
$version
	Icarus Verilog
$end
$timescale
	1ps
$end
$scope module tb_link_top $end
$var wire 1 ! done $end
$var reg 1 " clk $end
$var reg 1 # rst $end
$scope module dut $end
$var wire 1 " clk $end
$var wire 1 # rst $end
$var wire 1 $ req $end
$var wire 8 % last_byte [7:0] $end
$var wire 1 ! done $end
$var wire 8 & data [7:0] $end
$var wire 1 ' ack $end
$scope module u_master $end
$var wire 1 " clk $end
$var wire 1 # rst $end
$var wire 1 ' ack $end
$var parameter 3 ( CHECK_COUNT $end
$var parameter 3 ) DONE_STATE $end
$var parameter 3 * DROP_REQ $end
$var parameter 3 + IDLE $end
$var parameter 3 , SEND_REQ $end
$var parameter 3 - WAIT_ACK $end
$var parameter 3 . WAIT_ACK_LOW $end
$var reg 2 / byte_cnt [1:0] $end
$var reg 8 0 data [7:0] $end
$var reg 1 ! done $end
$var reg 3 1 next_state [2:0] $end
$var reg 1 $ req $end
$var reg 3 2 state [2:0] $end
$upscope $end
$scope module u_slave $end
$var wire 1 " clk $end
$var wire 8 3 data_in [7:0] $end
$var wire 1 $ req $end
$var wire 1 # rst $end
$var parameter 3 4 HOLD1 $end
$var parameter 3 5 HOLD2 $end
$var parameter 3 6 IDLE $end
$var parameter 3 7 LATCH $end
$var parameter 3 8 WAIT_REQ_LOW $end
$var reg 1 ' ack $end
$var reg 8 9 last_byte [7:0] $end
$var reg 3 : next_state [2:0] $end
$var reg 3 ; state [2:0] $end
$upscope $end
$upscope $end
$upscope $end
$enddefinitions $end
$comment Show the parameter values. $end
$dumpall
b100 8
b1 7
b0 6
b11 5
b10 4
b100 .
b10 -
b1 ,
b0 +
b11 *
b110 )
b101 (
$end
#0
$dumpvars
b0 ;
b0 :
b0 9
b0 3
b0 2
b1 1
b0 0
b0 /
0'
b0 &
b0 %
0$
1#
0"
0!
$end
#5000
1"
#10000
0"
#15000
b10 1
b1 :
b1 2
1$
1"
0#
#20000
0"
#25000
b10 :
b11 1
1'
b1 ;
b10 2
1"
#30000
0"
#35000
b100 1
b11 :
b11 2
0$
b10 ;
1"
#40000
0"
#45000
b100 :
b11 ;
b100 2
1"
#50000
0"
#55000
b0 :
b101 1
b100 ;
0'
1"
#60000
0"
#65000
b1 1
b0 ;
b101 2
1"
#70000
0"
#75000
b10 1
b1 :
b1 /
b1 2
1$
1"
#80000
0"
#85000
b10 :
b11 1
1'
b1 ;
b10 2
1"
#90000
0"
#95000
b100 1
b11 :
b11 2
0$
b10 ;
1"
#100000
0"
#105000
b100 :
b11 ;
b100 2
1"
#110000
0"
#115000
b0 :
b101 1
b100 ;
0'
1"
#120000
0"
#125000
b1 1
b0 ;
b101 2
1"
#130000
0"
#135000
b10 1
b1 :
b10 /
b1 2
b1 &
b1 0
b1 3
1$
1"
#140000
0"
#145000
b10 :
b11 1
1'
b1 %
b1 9
b1 ;
b10 2
1"
#150000
0"
#155000
b100 1
b11 :
b11 2
0$
b10 ;
1"
#160000
0"
#165000
b100 :
b11 ;
b100 2
1"
#170000
0"
#175000
b0 :
b101 1
b100 ;
0'
1"
#180000
0"
#185000
b1 1
b0 ;
b101 2
1"
#190000
0"
#195000
b10 1
b1 :
b11 /
b1 2
b10 &
b10 0
b10 3
1$
1"
#200000
0"
#205000
b10 :
b11 1
1'
b10 %
b10 9
b1 ;
b10 2
1"
#210000
0"
#215000
b100 1
b11 :
b11 2
0$
b10 ;
1"
#220000
0"
#225000
b100 :
b11 ;
b100 2
1"
#230000
0"
#235000
b0 :
b101 1
b100 ;
0'
1"
#240000
0"
#245000
b110 1
b0 ;
b101 2
1"
#250000
0"
#255000
b110 2
1!
1"
